{
  "project_info": {
    "project_number": "942540594831",
    "project_id": "aplicacaomovel-da6aa",
    "storage_bucket": "aplicacaomovel-da6aa.firebasestorage.app"
  },
  "client": [
    {
      "client_info": {
        "mobilesdk_app_id": "1:942540594831:android:f564b1304fdec01bfddafa",
        "android_client_info": {
          "package_name": "com.example.aplicacaomovel"
        }
      },
      "oauth_client": [],
      "api_key": [
        {
          "current_key": "AIzaSyCX-lLj7Cw5Kt6KjoRft0D8I6xkJTp8kHQ"
        }
      ],
      "services": {
        "appinvite_service": {
          "other_platform_oauth_client": []
        }
      }
    }
  ],
  "configuration_version": "1"
}